django_auto_drf/__init__.py
django_auto_drf/apps.py
django_auto_drf/auto_register.py
django_auto_drf/core.py
django_auto_drf/discovery.py
django_auto_drf/exceptions.py
django_auto_drf/permissions.py
django_auto_drf/registry.py
django_auto_drf/serializers.py
django_auto_drf/settings.py
django_auto_drf/urls.py
django_auto_drf/versioning.py
django_auto_drf/views.py
django_auto_drf/audit/__init__.py
django_auto_drf/audit/admin.py
django_auto_drf/audit/apps.py
django_auto_drf/audit/handlers.py
django_auto_drf/audit/models.py
django_auto_drf/audit/utils.py
django_auto_drf/audit/migrations/0001_initial.py
django_auto_drf/audit/migrations/__init__.py
django_auto_drf/audit/templates/admin/audit_assign_to_group.html
django_auto_drf/management/__init__.py
django_auto_drf/management/commands/__init__.py
django_auto_drf/management/commands/generate_ts_models.py
django_auto_drf-0.6.8.dist-info/licenses/LICENSE
django_auto_drf-0.6.8.dist-info/METADATA
django_auto_drf-0.6.8.dist-info/WHEEL
django_auto_drf-0.6.8.dist-info/top_level.txt
django_auto_drf-0.6.8.dist-info/RECORD
