Metadata-Version: 2.4
Name: django-auto-drf
Version: 0.6.8
Summary: Automated API registration for Django Rest Framework
Author-email: Marco Camplese <marcocamplesemc@gmail.com>
License:                     GNU GENERAL PUBLIC LICENSE
Project-URL: Homepage, https://github.com/wolfmc3/django-auto-drf
Project-URL: Documentation, https://github.com/wolfmc3/django-auto-drf/wiki
Project-URL: Source, https://github.com/wolfmc3/django-auto-drf
Project-URL: Issues, https://github.com/wolfmc3/django-auto-drf/issues
Keywords: django,rest-framework,api,automation
Classifier: Development Status :: 3 - Alpha
Classifier: Intended Audience :: Developers
Classifier: License :: OSI Approved :: GNU General Public License v3 (GPLv3)
Classifier: Programming Language :: Python :: 3
Classifier: Framework :: Django
Classifier: Framework :: Django :: 3.2
Classifier: Framework :: Django :: 4.0
License-File: LICENSE
Requires-Dist: Django>=3.2
Requires-Dist: djangorestframework>=3.12
Requires-Dist: django-filter>=2.4
Requires-Dist: drf-spectacular>=0.22.0
Dynamic: license-file
